[
    {
        "il_id": "manisa",
        "il_adi": "MANİSA",
        "il_kodu": 45,
        "ilce_id": "manisa-sehzadeler",
        "mahalle": "GÜZELKÖY MAH.",
        "ilce_adi": "ŞEHZADELER",
        "okul_adi": "GÜZELKÖY ÇOK AMAÇLI SALONU",
        "sandik_no": 1159,
        "mahalle_id": "manisa-sehzadeler-guzelkoy-mah",
        "ovo_mv_sonuc": {
            "toplam_oy": null,
            "sayim_sonuc": null,
            "tutanak_url": null,
            "oyveotesi_submission_id": null,
            "oyveotesi_sync_timestamp": 1684396858
        },
        "ovo_cb1_sonuc": {
            "toplam_oy": null,
            "sayim_sonuc": null,
            "tutanak_url": null,
            "oyveotesi_submission_id": null,
            "oyveotesi_sync_timestamp": 1684396858
        },
        "secim_bolge_id": "manisa"
    }
]