[
    {
        "il_id": "sirnak",
        "il_adi": "ŞIRNAK",
        "il_kodu": 73,
        "ilce_id": "sirnak-merkez",
        "mahalle": "ATBAŞI KÖYÜ",
        "ilce_adi": "ŞIRNAK MERKEZ",
        "okul_adi": "KIZILSU ŞH.A.VAHAP ÜSTÜNER İLKOKULU",
        "sandik_no": 1155,
        "mahalle_id": "sirnak-merkez-atbasi-koyu",
        "ovo_mv_sonuc": {
            "toplam_oy": 133,
            "sayim_sonuc": {
                "TOPLAM": 133,
                "SOL PARTİ": 0,
                "GENÇ PARTİ": 2,
                "İYİ PARTİ": 1,
                "VATAN PARTİSİ": 0,
                "ZAFER PARTİSİ": 22,
                "ADALET PARTİSİ": 1,
                "MİLLET PARTİSİ": 0,
                "ANAVATAN PARTİSİ": 1,
                "MEMLEKET PARTİSİ": 1,
                "YENİLİK PARTİSİ": 0,
                "MİLLİ YOL PARTİSİ": 0,
                "YENİDEN REFAH PARTİSİ": 2,
                "ADALET BİRLİK PARTİSİ": 0,
                "BÜYÜK BİRLİK PARTİSİ": 0,
                "CUMHURİYET HALK PARTİSİ": 7,
                "HALKIN KURTULUŞ PARTİSİ": 0,
                "GÜÇ BİRLİĞİ PARTİSİ": 0,
                "ADALET VE KALKINMA PARTİSİ": 82,
                "TÜRKİYE İŞÇİ PARTİSİ": 0,
                "TÜRKİYE KOMÜNİST HAREKETİ": 0,
                "TÜRKİYE KOMÜNİST PARTİSİ": 0,
                "HAK VE ÖZGÜRLÜKLER PARTİSİ": 0,
                "MİLLİYETÇİ HAREKET PARTİSİ": 11,
                "YEŞİLLER VE SOL GELECEK PARTİSİ": 3
            },
            "tutanak_url": "https://github.com/secim-tr/secim-2023-mayis-sirnak-tutanaklari/blob/main/tutanak/sirnak/sirnak-merkez/1xxx/1155/sirnak-merkez-1155-mv-000.jpg?raw=true",
            "oyveotesi_submission_id": "178847",
            "oyveotesi_sync_timestamp": 1684370625
        },
        "ovo_cb1_sonuc": {
            "toplam_oy": 141,
            "sayim_sonuc": {
                "TOPLAM": 141,
                "SİNAN OĞAN": 25,
                "MUHARREM İNCE": 2,
                "KEMAL KILIÇDAROĞLU": 20,
                "RECEP TAYYİP ERDOĞAN": 94
            },
            "tutanak_url": "https://github.com/secim-tr/secim-2023-mayis-sirnak-tutanaklari/blob/main/tutanak/sirnak/sirnak-merkez/1xxx/1155/sirnak-merkez-1155-cb1-000.jpg?raw=true",
            "oyveotesi_submission_id": "178847",
            "oyveotesi_sync_timestamp": 1684370625
        },
        "secim_bolge_id": "sirnak"
    }
]