[
    {
        "il_id": "denizli",
        "il_adi": "DENİZLİ",
        "il_kodu": 20,
        "ilce_id": "denizli-cameli",
        "mahalle": "YENİ MAH.",
        "ilce_adi": "ÇAMELİ",
        "okul_adi": "ATATÜRK İLKÖĞRETİM OKULU",
        "sandik_no": 1045,
        "mahalle_id": "denizli-cameli-yeni-mah",
        "ovo_mv_sonuc": {
            "toplam_oy": null,
            "sayim_sonuc": null,
            "tutanak_url": null,
            "oyveotesi_submission_id": null,
            "oyveotesi_sync_timestamp": 1684365634
        },
        "ovo_cb1_sonuc": {
            "toplam_oy": 289,
            "sayim_sonuc": {
                "TOPLAM": 289,
                "SİNAN OĞAN": 11,
                "MUHARREM İNCE": 2,
                "KEMAL KILIÇDAROĞLU": 168,
                "RECEP TAYYİP ERDOĞAN": 108
            },
            "tutanak_url": "https://github.com/secim-tr/secim-2023-mayis-denizli-tutanaklari/blob/main/tutanak/denizli/denizli-cameli/1xxx/1045/denizli-cameli-1045-cb1-000.jpg?raw=true",
            "oyveotesi_submission_id": null,
            "oyveotesi_sync_timestamp": 1684365634
        },
        "secim_bolge_id": "denizli"
    },
    {
        "il_id": "denizli",
        "il_adi": "DENİZLİ",
        "il_kodu": 20,
        "ilce_id": "denizli-cameli",
        "mahalle": "YENİ MAH.",
        "ilce_adi": "ÇAMELİ",
        "okul_adi": "ATATÜRK İLKÖĞRETİM OKULU",
        "sandik_no": 1046,
        "mahalle_id": "denizli-cameli-yeni-mah",
        "ovo_mv_sonuc": {
            "toplam_oy": null,
            "sayim_sonuc": null,
            "tutanak_url": null,
            "oyveotesi_submission_id": null,
            "oyveotesi_sync_timestamp": 1684365634
        },
        "ovo_cb1_sonuc": {
            "toplam_oy": null,
            "sayim_sonuc": null,
            "tutanak_url": null,
            "oyveotesi_submission_id": null,
            "oyveotesi_sync_timestamp": 1684365634
        },
        "secim_bolge_id": "denizli"
    },
    {
        "il_id": "denizli",
        "il_adi": "DENİZLİ",
        "il_kodu": 20,
        "ilce_id": "denizli-cameli",
        "mahalle": "YENİ MAH.",
        "ilce_adi": "ÇAMELİ",
        "okul_adi": "ATATÜRK İLKÖĞRETİM OKULU",
        "sandik_no": 1047,
        "mahalle_id": "denizli-cameli-yeni-mah",
        "ovo_mv_sonuc": {
            "toplam_oy": 283,
            "sayim_sonuc": {
                "TOPLAM": 283,
                "SOL PARTİ": 0,
                "GENÇ PARTİ": 0,
                "İYİ PARTİ": 39,
                "VATAN PARTİSİ": 0,
                "ZAFER PARTİSİ": 8,
                "ADALET PARTİSİ": 0,
                "MİLLET PARTİSİ": 0,
                "ANAVATAN PARTİSİ": 0,
                "MEMLEKET PARTİSİ": 6,
                "YENİLİK PARTİSİ": 0,
                "MİLLİ YOL PARTİSİ": 0,
                "YENİDEN REFAH PARTİSİ": 5,
                "ADALET BİRLİK PARTİSİ": 0,
                "BÜYÜK BİRLİK PARTİSİ": 2,
                "CUMHURİYET HALK PARTİSİ": 100,
                "HALKIN KURTULUŞ PARTİSİ": 1,
                "GÜÇ BİRLİĞİ PARTİSİ": 0,
                "ADALET VE KALKINMA PARTİSİ": 79,
                "TÜRKİYE İŞÇİ PARTİSİ": 2,
                "TÜRKİYE KOMÜNİST HAREKETİ": 0,
                "TÜRKİYE KOMÜNİST PARTİSİ": 0,
                "HAK VE ÖZGÜRLÜKLER PARTİSİ": 0,
                "MİLLİYETÇİ HAREKET PARTİSİ": 39,
                "YEŞİLLER VE SOL GELECEK PARTİSİ": 2
            },
            "tutanak_url": "https://github.com/secim-tr/secim-2023-mayis-denizli-tutanaklari/blob/main/tutanak/denizli/denizli-cameli/1xxx/1047/denizli-cameli-1047-mv-000.jpg?raw=true",
            "oyveotesi_submission_id": "768135",
            "oyveotesi_sync_timestamp": 1684365634
        },
        "ovo_cb1_sonuc": {
            "toplam_oy": 281,
            "sayim_sonuc": {
                "TOPLAM": 281,
                "SİNAN OĞAN": 25,
                "MUHARREM İNCE": 3,
                "KEMAL KILIÇDAROĞLU": 142,
                "RECEP TAYYİP ERDOĞAN": 111
            },
            "tutanak_url": "https://github.com/secim-tr/secim-2023-mayis-denizli-tutanaklari/blob/main/tutanak/denizli/denizli-cameli/1xxx/1047/denizli-cameli-1047-cb1-000.jpg?raw=true",
            "oyveotesi_submission_id": "768135",
            "oyveotesi_sync_timestamp": 1684365634
        },
        "secim_bolge_id": "denizli"
    },
    {
        "il_id": "denizli",
        "il_adi": "DENİZLİ",
        "il_kodu": 20,
        "ilce_id": "denizli-cameli",
        "mahalle": "YENİ MAH.",
        "ilce_adi": "ÇAMELİ",
        "okul_adi": "ATATÜRK İLKÖĞRETİM OKULU",
        "sandik_no": 1048,
        "mahalle_id": "denizli-cameli-yeni-mah",
        "ovo_mv_sonuc": {
            "toplam_oy": null,
            "sayim_sonuc": null,
            "tutanak_url": null,
            "oyveotesi_submission_id": null,
            "oyveotesi_sync_timestamp": 1684365634
        },
        "ovo_cb1_sonuc": {
            "toplam_oy": 271,
            "sayim_sonuc": {
                "TOPLAM": 271,
                "SİNAN OĞAN": 34,
                "MUHARREM İNCE": 1,
                "KEMAL KILIÇDAROĞLU": 113,
                "RECEP TAYYİP ERDOĞAN": 123
            },
            "tutanak_url": "https://github.com/secim-tr/secim-2023-mayis-denizli-tutanaklari/blob/main/tutanak/denizli/denizli-cameli/1xxx/1048/denizli-cameli-1048-cb1-000.jpg?raw=true",
            "oyveotesi_submission_id": null,
            "oyveotesi_sync_timestamp": 1684365634
        },
        "secim_bolge_id": "denizli"
    },
    {
        "il_id": "denizli",
        "il_adi": "DENİZLİ",
        "il_kodu": 20,
        "ilce_id": "denizli-cameli",
        "mahalle": "YENİ MAH.",
        "ilce_adi": "ÇAMELİ",
        "okul_adi": "ATATÜRK İLKÖĞRETİM OKULU",
        "sandik_no": 1049,
        "mahalle_id": "denizli-cameli-yeni-mah",
        "ovo_mv_sonuc": {
            "toplam_oy": 298,
            "sayim_sonuc": {
                "TOPLAM": 298,
                "SOL PARTİ": 0,
                "GENÇ PARTİ": 0,
                "İYİ PARTİ": 36,
                "VATAN PARTİSİ": 0,
                "ZAFER PARTİSİ": 9,
                "ADALET PARTİSİ": 0,
                "MİLLET PARTİSİ": 0,
                "ANAVATAN PARTİSİ": 0,
                "MEMLEKET PARTİSİ": 3,
                "YENİLİK PARTİSİ": 0,
                "MİLLİ YOL PARTİSİ": 0,
                "YENİDEN REFAH PARTİSİ": 0,
                "ADALET BİRLİK PARTİSİ": 0,
                "BÜYÜK BİRLİK PARTİSİ": 3,
                "CUMHURİYET HALK PARTİSİ": 119,
                "HALKIN KURTULUŞ PARTİSİ": 0,
                "GÜÇ BİRLİĞİ PARTİSİ": 0,
                "ADALET VE KALKINMA PARTİSİ": 91,
                "TÜRKİYE İŞÇİ PARTİSİ": 3,
                "TÜRKİYE KOMÜNİST HAREKETİ": 0,
                "TÜRKİYE KOMÜNİST PARTİSİ": 0,
                "HAK VE ÖZGÜRLÜKLER PARTİSİ": 0,
                "MİLLİYETÇİ HAREKET PARTİSİ": 34,
                "YEŞİLLER VE SOL GELECEK PARTİSİ": 0
            },
            "tutanak_url": "https://github.com/secim-tr/secim-2023-mayis-denizli-tutanaklari/blob/main/tutanak/denizli/denizli-cameli/1xxx/1049/denizli-cameli-1049-mv-000.jpg?raw=true",
            "oyveotesi_submission_id": "765313",
            "oyveotesi_sync_timestamp": 1684365634
        },
        "ovo_cb1_sonuc": {
            "toplam_oy": 304,
            "sayim_sonuc": {
                "TOPLAM": 304,
                "SİNAN OĞAN": 22,
                "MUHARREM İNCE": 3,
                "KEMAL KILIÇDAROĞLU": 152,
                "RECEP TAYYİP ERDOĞAN": 127
            },
            "tutanak_url": "https://github.com/secim-tr/secim-2023-mayis-denizli-tutanaklari/blob/main/tutanak/denizli/denizli-cameli/1xxx/1049/denizli-cameli-1049-cb1-000.jpg?raw=true",
            "oyveotesi_submission_id": "765313",
            "oyveotesi_sync_timestamp": 1684365634
        },
        "secim_bolge_id": "denizli"
    }
]