[
    {
        "il_id": "sinop",
        "il_adi": "SİNOP",
        "il_kodu": 57,
        "ilce_id": "sinop-ayancik",
        "mahalle": "ÇAYİÇİ MAH.",
        "ilce_adi": "AYANCIK",
        "okul_adi": "MESLEKİ VE TEKNİK ANADOLU LİSESİ",
        "sandik_no": 1019,
        "mahalle_id": "sinop-ayancik-cayici-mah",
        "ovo_mv_sonuc": {
            "toplam_oy": null,
            "sayim_sonuc": null,
            "tutanak_url": null,
            "oyveotesi_submission_id": null,
            "oyveotesi_sync_timestamp": 1684355663
        },
        "ovo_cb1_sonuc": {
            "toplam_oy": null,
            "sayim_sonuc": null,
            "tutanak_url": null,
            "oyveotesi_submission_id": null,
            "oyveotesi_sync_timestamp": 1684355663
        },
        "secim_bolge_id": "sinop"
    },
    {
        "il_id": "sinop",
        "il_adi": "SİNOP",
        "il_kodu": 57,
        "ilce_id": "sinop-ayancik",
        "mahalle": "ÇAYİÇİ MAH.",
        "ilce_adi": "AYANCIK",
        "okul_adi": "MESLEKİ VE TEKNİK ANADOLU LİSESİ",
        "sandik_no": 1020,
        "mahalle_id": "sinop-ayancik-cayici-mah",
        "ovo_mv_sonuc": {
            "toplam_oy": null,
            "sayim_sonuc": null,
            "tutanak_url": null,
            "oyveotesi_submission_id": null,
            "oyveotesi_sync_timestamp": 1684355663
        },
        "ovo_cb1_sonuc": {
            "toplam_oy": null,
            "sayim_sonuc": null,
            "tutanak_url": null,
            "oyveotesi_submission_id": null,
            "oyveotesi_sync_timestamp": 1684355663
        },
        "secim_bolge_id": "sinop"
    },
    {
        "il_id": "sinop",
        "il_adi": "SİNOP",
        "il_kodu": 57,
        "ilce_id": "sinop-ayancik",
        "mahalle": "ÇAYİÇİ MAH.",
        "ilce_adi": "AYANCIK",
        "okul_adi": "MESLEKİ VE TEKNİK ANADOLU LİSESİ",
        "sandik_no": 1018,
        "mahalle_id": "sinop-ayancik-cayici-mah",
        "ovo_mv_sonuc": {
            "toplam_oy": 213,
            "sayim_sonuc": {
                "TOPLAM": 213,
                "GENÇ PARTİ": 2,
                "İYİ PARTİ": 20,
                "ZAFER PARTİSİ": 6,
                "ADALET PARTİSİ": 1,
                "ANAVATAN PARTİSİ": 1,
                "MEMLEKET PARTİSİ": 1,
                "YENİDEN REFAH PARTİSİ": 2,
                "BÜYÜK BİRLİK PARTİSİ": 10,
                "CUMHURİYET HALK PARTİSİ": 69,
                "HALKIN KURTULUŞ PARTİSİ": 1,
                "ADALET VE KALKINMA PARTİSİ": 77,
                "TÜRKİYE İŞÇİ PARTİSİ": 3,
                "MİLLİYETÇİ HAREKET PARTİSİ": 20
            },
            "tutanak_url": "https://github.com/secim-tr/secim-2023-mayis-sinop-tutanaklari/blob/main/tutanak/sinop/sinop-ayancik/1xxx/1018/sinop-ayancik-1018-mv-000.jpg?raw=true",
            "oyveotesi_submission_id": "205722",
            "oyveotesi_sync_timestamp": 1684355663
        },
        "ovo_cb1_sonuc": {
            "toplam_oy": 213,
            "sayim_sonuc": {
                "TOPLAM": 213,
                "SİNAN OĞAN": 11,
                "MUHARREM İNCE": 2,
                "KEMAL KILIÇDAROĞLU": 88,
                "RECEP TAYYİP ERDOĞAN": 112
            },
            "tutanak_url": "https://github.com/secim-tr/secim-2023-mayis-sinop-tutanaklari/blob/main/tutanak/sinop/sinop-ayancik/1xxx/1018/sinop-ayancik-1018-cb1-000.jpg?raw=true",
            "oyveotesi_submission_id": "205722",
            "oyveotesi_sync_timestamp": 1684355663
        },
        "secim_bolge_id": "sinop"
    },
    {
        "il_id": "sinop",
        "il_adi": "SİNOP",
        "il_kodu": 57,
        "ilce_id": "sinop-ayancik",
        "mahalle": "ÇAYİÇİ MAH.",
        "ilce_adi": "AYANCIK",
        "okul_adi": "CUMHURİYET İLKÖĞRETİM OKULU",
        "sandik_no": 1017,
        "mahalle_id": "sinop-ayancik-cayici-mah",
        "ovo_mv_sonuc": {
            "toplam_oy": null,
            "sayim_sonuc": null,
            "tutanak_url": null,
            "oyveotesi_submission_id": null,
            "oyveotesi_sync_timestamp": 1684355663
        },
        "ovo_cb1_sonuc": {
            "toplam_oy": null,
            "sayim_sonuc": null,
            "tutanak_url": null,
            "oyveotesi_submission_id": null,
            "oyveotesi_sync_timestamp": 1684355663
        },
        "secim_bolge_id": "sinop"
    },
    {
        "il_id": "sinop",
        "il_adi": "SİNOP",
        "il_kodu": 57,
        "ilce_id": "sinop-ayancik",
        "mahalle": "ÇAYİÇİ MAH.",
        "ilce_adi": "AYANCIK",
        "okul_adi": "CUMHURİYET İLKÖĞRETİM OKULU",
        "sandik_no": 1016,
        "mahalle_id": "sinop-ayancik-cayici-mah",
        "ovo_mv_sonuc": {
            "toplam_oy": null,
            "sayim_sonuc": null,
            "tutanak_url": null,
            "oyveotesi_submission_id": null,
            "oyveotesi_sync_timestamp": 1684355663
        },
        "ovo_cb1_sonuc": {
            "toplam_oy": null,
            "sayim_sonuc": null,
            "tutanak_url": null,
            "oyveotesi_submission_id": null,
            "oyveotesi_sync_timestamp": 1684355663
        },
        "secim_bolge_id": "sinop"
    }
]